{"trial_id": "08", "hyperparameters": {"space": [{"class_name": "Choice", "config": {"name": "lr_g", "default": 1e-05, "conditions": [], "values": [1e-05, 0.0001, 0.001], "ordered": true}}, {"class_name": "Int", "config": {"name": "n_fc_g", "default": null, "conditions": [], "min_value": 2, "max_value": 5, "step": 1, "sampling": null}}, {"class_name": "Int", "config": {"name": "hidden_phi_g", "default": null, "conditions": [], "min_value": 4, "max_value": 48, "step": 4, "sampling": null}}, {"class_name": "Int", "config": {"name": "n_fc_d", "default": null, "conditions": [], "min_value": 2, "max_value": 5, "step": 1, "sampling": null}}, {"class_name": "Int", "config": {"name": "hidden_phi_d", "default": null, "conditions": [], "min_value": 4, "max_value": 48, "step": 4, "sampling": null}}, {"class_name": "Choice", "config": {"name": "batch_size_g", "default": 64, "conditions": [], "values": [64, 128, 256, 512], "ordered": true}}], "values": {"lr_g": 0.001, "n_fc_g": 3, "hidden_phi_g": 44, "n_fc_d": 5, "hidden_phi_d": 44, "batch_size_g": 128}}, "metrics": {"metrics": {"d_loss": {"direction": "min", "observations": [{"value": [0.335226833820343], "step": 20}]}, "g_loss": {"direction": "min", "observations": [{"value": [-0.6105705499649048], "step": 20}]}, "val_d_loss": {"direction": "min", "observations": [{"value": [0.5336300730705261], "step": 20}]}, "val_g_loss": {"direction": "min", "observations": [{"value": [-0.9097981452941895], "step": 20}]}}}, "score": 0.5336300730705261, "best_step": 20, "status": "COMPLETED"}